pipinstaller/__init__.py
pipinstaller/pipinstaller.py
pipinstaller-0.1.dist-info/LICENSE
pipinstaller-0.1.dist-info/METADATA
pipinstaller-0.1.dist-info/WHEEL
pipinstaller-0.1.dist-info/entry_points.txt
pipinstaller-0.1.dist-info/top_level.txt
pipinstaller-0.1.dist-info/RECORD
