Metadata-Version: 2.1
Name: pipinstaller
Version: 0.1
Summary: A package to install banch of  packages from a pypi.org .
Author: Souporno Chakraborty
Author-email: shrabanichakraborty83@gmail.com
License-File: LICENSE
Requires-Dist: requests
